{
    "timestamp": 1743163299890,
    "analyses": [
        "removeAnalysis2_81pi5m4t",
        "František je borec",
        "Toto je povolený tag.",
        "analysis_50dhv31a",
        "removeAnalysis2_0e027fyp"
    ],
    "uploaded": 1750857558000,
    "tags": [
        "removeTag2_81pi5m4t",
        "Tohle se nesmí;alert(1))",
        "obsah Mimo obsah.",
        "testTag1_50dhv31a",
        "testTag2_50dhv31a",
        "removeTag2_0e027fyp"
    ],
    "label": "A B C D E F G",
    "description": "Popiska zůstane Toto by mělo zůstat.odstavec Mimo odstavec."
}